dfplanner/__init__.py
dfplanner/plan.py
dfplanner/tracer.py
dfplanner-0.0.2.dist-info/LICENSE.txt
dfplanner-0.0.2.dist-info/WHEEL
dfplanner-0.0.2.dist-info/METADATA
dfplanner-0.0.2.dist-info/RECORD
